pedlam/Driver.py
pedlam/__init__.py
pedlam/helpers/PackageHelper.py
pedlam/helpers/__init__.py
pedlam_scripts/__init__.py
pedlam_scripts/pedlam_cli.py
pedlam-0.0.1.dist-info/METADATA
pedlam-0.0.1.dist-info/WHEEL
pedlam-0.0.1.dist-info/entry_points.txt
pedlam-0.0.1.dist-info/top_level.txt
pedlam-0.0.1.dist-info/RECORD
